<?xml version="1.0"?>
<Settings>
  <Namespace></Namespace>
  <Compiler>
      <SourceFileOptions>local</SourceFileOptions>
      <SourceFileFolder></SourceFileFolder>
      <OutputFile></OutputFile>
      <Debug>false</Debug>
      <Optimize>false</Optimize>
      <Incremental>false</Incremental>
      <WarningAsErrors>false</WarningAsErrors>
      <XMLDocFiles></XMLDocFiles>
      <CompilerCommandLine>/t:library /r:System.dll,System.Data.dll,System.Web.dll,System.Data.dll,System.Web.Services.dll,System.XML.dll</CompilerCommandLine>
      <SiteRoot>false</SiteRoot>
      <ServerModel>false</ServerModel>
      <UTF8Output>false</UTF8Output>
      <WarningLevel>2</WarningLevel>
  </Compiler>
</Settings>
